[
    {
        "id":1
    },
    {
        "id":2,
        "nome":"Beltrano",
        "endereco":"Rua do Beltrano",
        "cep":"12345678",
        "data_de_nascimento":"1995-12-17T05:24:00.000Z",
        "telefone":53111122222
    },
    {
        "id":3,
        "nome":"Eltrano",
        "endereco":"Rua do Eltrano",
        "cep":"12345678",
        "data_de_nascimento":"1995-12-17T05:24:00.000Z",
        "telefone":53111122222
    },
    {
        "id":4
    },{
        "id":5,
        "nome":"Eltrano",
        "endereco":"Rua do Eltrano",
        "cep":"12345678",
        "data_de_nascimento":"1995-12-17T05:24:00.000Z",
        "telefone":53111122222
    },
    {
        "id":6
    },
    {
        "id":7,
        "nome":"Eltrano",
        "endereco":"Rua do Eltrano",
        "cep":"12345678",
        "data_de_nascimento":"1995-12-17T05:24:00.000Z",
        "telefone":53111122222
    },
    {
        "id":8,
        "nome":"Eltrano",
        "endereco":"Rua do Eltrano",
        "cep":"12345678",
        "data_de_nascimento":"1995-12-17T05:24:00.000Z",
        "telefone":53111122222
    }
]